simplecsv/SimpleCsv.py
simplecsv/__init__.py
simplecsv-0.2.1.dist-info/LICENSE
simplecsv-0.2.1.dist-info/METADATA
simplecsv-0.2.1.dist-info/WHEEL
simplecsv-0.2.1.dist-info/top_level.txt
simplecsv-0.2.1.dist-info/RECORD
